{
  "catagory": [
    {
      "id": 0,
      "categoryName": "Dükan bazarlıq",
      "img": "https://strgimgr.umico.az/catalog/07490f2be1502197afc14b22f00097d5.svg",
      "subCategories": [
        {
          "id": 1,
          "name": "Meyvə və tərəvəz"
        },
        {
          "id": 2,
          "name": "Ət, toyuq və dəniz məhsulları"
        },
        {
          "id": 3,
          "name": "Sosis və kolbasalar"
        },
        {
          "id": 4,
          "name": "Yumurta, pendir və yağlar"
        },
        {
          "id": 5,
          "name": "Süd məhsulları"
        },
        {
          "id": 6,
          "name": "Yoğurtlar və südli desertlər"
        },
        {
          "id": 7,
          "name": "Çörək məhsulları"
        },
        {
          "id": 8,
          "name": "Alkoqolsuz içkilər"
        },
        {
          "id": 9,
          "name": "Ev təmizliyi"
        },
        {
          "id": 10,
          "name": "Gigiyena və gözəllik"
        },
        {
          "id": 11,
          "name": "Makaronlar və paxlalı məhsullar"
        },
        {
          "id": 12,
          "name": "Yarımbişmiş və dondurulmuş qida"
        },
        {
          "id": 13,
          "name": "Un, şəkər tozu və bişirmə alətləri"
        },
        {
          "id": 14,
          "name": "Duru yağlar"
        },
        {
          "id": 15,
          "name": "Bal, cem və şokolad yağları"
        },
        {
          "id": 16,
          "name": "İsti içkilər"
        },
        {
          "id": 17,
          "name": "Şirniyyatlar"
        },
        {
          "id": 18,
          "name": "Səhər yeməyi"
        },
        {
          "id": 19,
          "name": "Çips və çərəz"
        },
        {
          "id": 20,
          "name": "Konserv və turşular"
        },
        {
          "id": 21,
          "name": "Souslar və ədviyyatlar"
        },
        {
          "id": 22,
          "name": "Dietik, diabetik və sağlam qida"
        },
        {
          "id": 23,
          "name": "Ev heyvanları üçün qida"
        },
        {
          "id": 24,
          "name": "Uşaqlar üçün"
        },
        {
          "id": 25,
          "name": "Saqqızlar"
        },
        {
          "id": 26,
          "name": "Dondurma"
        }
      ]
    },
    {
      "id": 1,
      "categoryName": "Telefonlar, Smart cihazlar və telefon aksesuarları",
      "img": "https://strgimgr.umico.az/catalog/24e53bfee14bef7a2daa54f7be754bf8.svg",
      "subcategory": [
        {
          "id": 1,
          "categoryName": "Mobil telefonlar və smartfonlar",
          "slug": "telefonlar-smart-cihazlar-aksesuarlar/mobil-telefonlar-ve-smartfonlar"
        },
        {
          "id": 2,
          "categoryName": "Ağıllı saatlar və fitnes qolbaqları",
          "slug": "telefonlar-smart-cihazlar-aksesuarlar/agilli-saatlar-ve-fitnes-qolbaqlari"
        },
        {
          "id": 3,
          "categoryName": "Stasionar telefonlar",
          "slug": "telefonlar-smart-cihazlar-aksesuarlar/stasionar-telefonlar"
        },
        {
          "id": 4,
          "categoryName": "IP-telefoniya, Mini ATS",
          "slug": "telefonlar-smart-cihazlar-aksesuarlar/ip-telefoniya-mini-ats"
        },
        {
          "id": 5,
          "categoryName": "Qulaqlıqlar və qarnituralar",
          "slug": "telefonlar-smart-cihazlar-aksesuarlar/qulaqliqlar-ve-qarnituralar"
        },
        {
          "id": 6,
          "categoryName": "Telefonlar və smartfonlar üçün aksesuarlar",
          "slug": "telefonlar-smart-cihazlar-aksesuarlar/telefonlar-ve-smartfonlar-ucun-aksesuarlar"
        },
        {
          "id": 7,
          "categoryName": "Ağıllı ev sistemləri",
          "slug": "telefonlar-smart-cihazlar-aksesuarlar/agilli-ev-sistemleri"
        }
      ]
    },
    {
      "id": 2,
      "categoryName": "Məişət texnikası",
      "img": "https://strgimgr.umico.az/catalog/021f0185c048c59a4bb779a46e4141c0.svg",
      "subcategory": [
        {
          "id": 1,
          "categoryName": "İri məişət texnikası",
          "slug": "meiset-texnikasi/iri-meiset-texnikasi"
        },
        {
          "id": 2,
          "categoryName": "Quraşdırılan texnika",
          "slug": "meiset-texnikasi/qurasdirilan-texnika"
        },
        {
          "id": 3,
          "categoryName": "Kondisionerlər və digər iqlim texnikası",
          "slug": "meiset-texnikasi/kondisionerler-ve-diger-iqlim-texnikasi"
        },
        {
          "id": 4,
          "categoryName": "Mətbəx üçün kiçik məişət texnikası",
          "slug": "meiset-texnikasi/metbex-ucun-kicik-meiset-texnikasi"
        },
        {
          "id": 5,
          "categoryName": "Ev üçün kiçik məişət texnikası",
          "slug": "meiset-texnikasi/ev-ucun-kicik-meiset-texnikasi"
        },
        {
          "id": 6,
          "categoryName": "Gözəllik və sağlamlıq üçün texnika",
          "slug": "meiset-texnikasi/gozellik-ve-saglamliq-ucun-texnika"
        }
      ]
    },
    {
      "id": 3,
      "categoryName": "Notbuk və kompüterlər",
      "img": "https://strgimgr.umico.az/catalog/2672d729fd7aeafb4c7360cd3a4c66c8.svg",
      "subcategory": [
        {
          "id": 1,
          "categoryName": "Notbuklar"
        },
        {
          "id": 2,
          "categoryName": "Planşetlər"
        },
        {
          "id": 3,
          "categoryName": "Qrafik planşetlər"
        },
        {
          "id": 4,
          "categoryName": "Masaüstü kompüterlər"
        },
        {
          "id": 5,
          "categoryName": "Monobloklar"
        },
        {
          "id": 6,
          "categoryName": "Monitorlar"
        },
        {
          "id": 7,
          "categoryName": "Klaviaturalar və kompüter siçanları"
        },
        {
          "id": 8,
          "categoryName": "Elektron kitablar"
        },
        {
          "id": 9,
          "categoryName": "Notbuk və kompüter hissələri"
        },
        {
          "id": 10,
          "categoryName": "Server avadanlığı"
        },
        {
          "id": 11,
          "categoryName": "Şəbəkə avadanlığı"
        },
        {
          "id": 12,
          "categoryName": "Ofis texnikası"
        },
        {
          "id": 13,
          "categoryName": "Oyun konsolları və aksessuarlar"
        },
        {
          "id": 14,
          "categoryName": "Notbuk və kompüter aksesuarları"
        }
      ]
    },
    {
      "id": 4,
      "categoryName": "TV, audio və video",
      "img": "https://strgimgr.umico.az/catalog/92eacf803553ed6a0c96698a34da6d71.svg",
      "subcategory": []
    },
    {
      "id": 5,
      "categoryName": "Ev əşyaları",
      "img": "https://strgimgr.umico.az/catalog/7e5d6bde52242733bfa11ee4d415d03b.svg",
      "subcategory": [
        {
          "id": 1,
          "name": "Qab-qacaq"
        },
        {
          "id": 2,
          "name": "Ev mebeli"
        },
        {
          "id": 3,
          "name": "Sobalar və kamınlar"
        },
        {
          "id": 4,
          "name": "Ev tekstili"
        },
        {
          "id": 5,
          "name": "Yuxu üçün məhsullar"
        },
        {
          "id": 6,
          "name": "Xalçalar və aksessuarlar"
        },
        {
          "id": 7,
          "name": "Dekor və interyer"
        },
        {
          "id": 8,
          "name": "Seyflər"
        },
        {
          "id": 9,
          "name": "Saxlama qabları"
        }
      ]
    },
    {
      "id": 6,
      "categoryName": "Gözəllik və Sağlamlıq",
      "img": "https://strgimgr.umico.az/catalog/18bd8d3879acd25e5840f04a21463631.svg",
      "subcategory": [
        {
          "id": 1,
          "name": "Ətirler"
        },
        {
          "id": 2,
          "name": "Makiyaj"
        },
        {
          "id": 3,
          "name": "Saçlara qulluq"
        },
        {
          "id": 4,
          "name": "Bədənə qulluq"
        },
        {
          "id": 5,
          "name": "Tibbi məhsullar"
        },
        {
          "id": 6,
          "name": "Uşaq üçün kosmetika və qulluq"
        }
      ]
    },
    {
      "id": 7,
      "categoryName": "Saat, zinət və bəzək əşyaları",
      "img": "https://strgimgr.umico.az/catalog/d9b6079fcc411177f741e30ab2940a9a.svg",
      "subcategory": []
    },
    {
      "id": 8,
      "categoryName": "Umico Gaming",
      "img": "https://strgimgr.umico.az/catalog/13b24247f5d394f1c72f8d3b1cdb99ed.svg",
      "subcategory": []
    },
    {
      "id": 9,
      "categoryName": "Təmir-tikinti",
      "img": "https://strgimgr.umico.az/catalog/d36b89db2ddbc2eff3ee4d1c988551a9.svg",
      "subcategory": []
    },
    {
      "id": 10,
      "categoryName": "Uşaqlar üçün məhsullar",
      "img": "https://strgimgr.umico.az/catalog/c541b77b9db12478d47e11f18c377811.svg",
      "subcategory": []
    },
    {
      "id": 11,
      "categoryName": "Ofis və məktəb ləvazimatları, kitablar",
      "img": "https://strgimgr.umico.az/catalog/6ecbf7e4fdcf2a268e2153d367e31714.svg",
      "subcategory": []
    },
    {
      "id": 12,
      "categoryName": "Ev heyvanları üçün məhsullar",
      "img": "https://strgimgr.umico.az/catalog/2d02d5acc242f11373c860b217594401.svg",
      "subcategory": []
    },
    {
      "id": 13,
      "categoryName": "Geyim, ayaqqabı və aksessuarlar",
      "img": "https://strgimgr.umico.az/catalog/32d25140cdf0f4ffd579ff7db2602ae6.svg",
      "subcategory": []
    },
    {
      "id": 14,
      "categoryName": "İdman və Əyləncə",
      "img": "https://strgimgr.umico.az/catalog/3ec9ee8280c23afabc4be3effb7dce20.svg",
      "subcategory": []
    },
    {
      "id": 15,
      "categoryName": "Avtomobil məhsulları",
      "img": "https://strgimgr.umico.az/catalog/c2b8b49e06e232a22e10187e60ca3dff.svg",
      "subcategory": []
    },
    {
      "id": 15,
      "categoryName": "Bağ üçün məhsullar",
      "img": "https://strgimgr.umico.az/catalog/a6e5fd8cc2f193387c8b6da70b57c450.svg",
      "subcategory": []
    },
    {
      "id": 15,
      "categoryName": "Outlet",
      "img": "https://strgimgr.umico.az/catalog/bf25fcc877f9cf3d9bcc3565abe776e5.svg",
      "subcategory": []
    }
  ],
  "UmicoBonus": [
    {
      "id": 1,
      "categoryName": "Supermarketlər",
      "img": "https://umico.az/images/categories/supermarkety.svg"
    },
    {
      "id": 2,
      "categoryName": "Restoran və kafelər",
      "img": "https://umico.az/images/categories/food_drink.svg"
    },
    {
      "id": 3,
      "categoryName": "Moda və stil",
      "img": "https://umico.az/images/categories/clothes.svg"
    },
    {
      "id": 4,
      "categoryName": "Qurğu və texnologiyalar",
      "img": "https://umico.az/images/categories/hobby_and_books.svg"
    },
    {
      "id": 5,
      "categoryName": "Gözəllik və sağlamlıq",
      "img": "https://umico.az/images/categories/parfume.svg"
    },
    {
      "id": 6,
      "categoryName": "Uşaq və analara",
      "img": "https://umico.az/images/categories/child.svg"
    },
    {
      "id": 7,
      "categoryName": "Ev və məişət",
      "img": "https://umico.az/images/categories/home.svg"
    },
    {
      "id": 8,
      "categoryName": "İstirahət və əyləncə",
      "img": "https://umico.az/images/categories/recreation_entertainment.svg"
    },
    {
      "id": 9,
      "categoryName": "İş və təhsil",
      "img": "https://umico.az/images/categories/education.svg"
    },
    {
      "id": 10,
      "categoryName": "Gəzinti və səyahətlər",
      "img": "https://umico.az/images/categories/education.svg"
    },
    {
      "id": 11,
      "categoryName": "Avto, moto və digər nəqliyyat",
      "img": "https://umico.az/images/categories/auto_moto.svg"
    }
  ]
}